[
null,
{"id":1,"animationId":3,"description":"A huge sword used exclusively by warriors.\n\"I've always wanted a huge cool sword!\"","etypeId":1,"traits":[{"code":31,"dataId":1,"value":0}],"iconIndex":97,"name":"Soldier Blade","note":"<book:no>\n","params":[0,0,10,0,0,0,0,0],"price":0,"wtypeId":1},
{"id":2,"animationId":3,"description":"A huge sword used exclusively by warriors.\n\"I've always wanted a huge cool sword!\"","etypeId":1,"traits":[{"code":31,"dataId":1,"value":0}],"iconIndex":97,"name":"Soldier Blade + 1","note":"<mat1:W1*1>\n<mat2:I161*5>\n<mat3:I162*5>\n<mat4:I163*5>\n<mat5:I164*5>\n<mat6:I165*5>\n<mat7:I166*5>\n\n<book:no>\n","params":[0,0,20,0,0,0,0,0],"price":0,"wtypeId":1},
{"id":3,"animationId":3,"description":"A huge sword used exclusively by warriors.\n\"I've always wanted a huge cool sword!\"","etypeId":1,"traits":[{"code":31,"dataId":1,"value":0}],"iconIndex":97,"name":"Soldier Blade + 2","note":"<mat1:W2*1>\n<mat2:I168*5>\n<mat3:I169*5>\n<mat4:I170*5>\n<mat5:I171*5>\n<mat6:I172*5>\n<mat7:I173*5>\n\n<book:no>\n","params":[0,0,35,0,0,0,0,0],"price":0,"wtypeId":1},
{"id":4,"animationId":3,"description":"A huge sword used exclusively by warriors.\n\"I've always wanted a huge cool sword!\"","etypeId":1,"traits":[{"code":31,"dataId":1,"value":0}],"iconIndex":97,"name":"Soldier Blade + 3","note":"<mat1:W3*1>\n<mat2:I175*5>\n<mat3:I176*5>\n<mat4:I177*5>\n<mat5:I178*5>\n<mat6:I179*5>\n<mat7:I180*5>\n\n<book:no>\n","params":[0,0,50,0,0,0,0,0],"price":0,"wtypeId":1},
{"id":5,"animationId":0,"description":"","etypeId":1,"traits":[{"code":31,"dataId":1,"value":0},{"code":22,"dataId":0,"value":0}],"iconIndex":0,"name":"","note":"","params":[0,0,0,0,0,0,0,0],"price":0,"wtypeId":0},
{"id":6,"animationId":0,"description":"","etypeId":1,"traits":[{"code":31,"dataId":1,"value":0},{"code":22,"dataId":0,"value":0}],"iconIndex":0,"name":"","note":"","params":[0,0,0,0,0,0,0,0],"price":0,"wtypeId":0},
{"id":7,"animationId":193,"description":"A standard staff used by mages across the world.\n\"It's bigger than me...\"","etypeId":1,"traits":[],"iconIndex":101,"name":"Magic Staff","note":"<CAG攻撃:3>\n<book:no>\n","params":[0,0,0,0,10,0,0,0],"price":0,"wtypeId":2},
{"id":8,"animationId":193,"description":"A standard staff used by mages across the world.\n\"It's bigger than me...\"","etypeId":1,"traits":[],"iconIndex":101,"name":"Magic Staff + 1","note":"<CAG攻撃:3>\n<mat1:W7*1>\n<mat2:I161*5>\n<mat3:I162*5>\n<mat4:I163*5>\n<mat5:I164*5>\n<mat6:I165*5>\n<mat7:I166*5>\n<book:no>\n","params":[0,0,0,0,20,0,0,0],"price":0,"wtypeId":2},
{"id":9,"animationId":193,"description":"A standard staff used by mages across the world.\n\"It's bigger than me...\"","etypeId":1,"traits":[],"iconIndex":101,"name":"Magic Staff + 2","note":"<CAG攻撃:3>\n<mat1:W8*1>\n<mat2:I168*5>\n<mat3:I169*5>\n<mat4:I170*5>\n<mat5:I171*5>\n<mat6:I172*5>\n<mat7:I173*5>\n<book:no>\n\n","params":[0,0,0,0,35,0,0,0],"price":0,"wtypeId":2},
{"id":10,"animationId":193,"description":"A standard staff used by mages across the world.\n\"It's bigger than me...\"","etypeId":1,"traits":[],"iconIndex":101,"name":"Magic Staff + 3","note":"<CAG攻撃:3>\n<mat1:W9*1>\n<mat2:I175*5>\n<mat3:I176*5>\n<mat4:I177*5>\n<mat5:I178*5>\n<mat6:I179*5>\n<mat7:I180*5>\n<book:no>\n\n\n","params":[0,0,0,0,50,0,0,0],"price":0,"wtypeId":2},
{"id":11,"animationId":0,"description":"","etypeId":1,"traits":[{"code":31,"dataId":1,"value":0},{"code":22,"dataId":0,"value":0}],"iconIndex":0,"name":"","note":"","params":[0,0,0,0,0,0,0,0],"price":0,"wtypeId":0},
{"id":12,"animationId":0,"description":"","etypeId":1,"traits":[{"code":31,"dataId":1,"value":0},{"code":22,"dataId":0,"value":0}],"iconIndex":0,"name":"","note":"","params":[0,0,0,0,0,0,0,0],"price":0,"wtypeId":0},
{"id":13,"animationId":0,"description":"Attacks that don't use the Soldier Blade.","etypeId":1,"traits":[{"code":31,"dataId":1,"value":0},{"code":22,"dataId":0,"value":0}],"iconIndex":97,"name":"Combat","note":"<Set Sts Data>\nskill: 46\n</Set Sts Data>\n\n<book:no>\n","params":[0,0,0,0,0,0,0,0],"price":0,"wtypeId":3},
{"id":14,"animationId":0,"description":"Special sword attacks.","etypeId":1,"traits":[{"code":31,"dataId":1,"value":0},{"code":22,"dataId":0,"value":0}],"iconIndex":97,"name":"Blade","note":"<Set Sts Data>\nskill: 31\n</Set Sts Data>\n\n<book:no>\n","params":[0,0,0,0,0,0,0,0],"price":0,"wtypeId":3},
{"id":15,"animationId":0,"description":"Enhance your basic stats.","etypeId":1,"traits":[{"code":31,"dataId":1,"value":0},{"code":22,"dataId":0,"value":0}],"iconIndex":97,"name":"Status","note":"<Set Sts Data>\nskill: 131,151,161,171,181\n</Set Sts Data>\n\n<book:no>\n","params":[0,0,0,0,0,0,0,0],"price":0,"wtypeId":3},
{"id":16,"animationId":0,"description":"Normal magic.","etypeId":1,"traits":[{"code":31,"dataId":1,"value":0},{"code":22,"dataId":0,"value":0}],"iconIndex":101,"name":"Magic","note":"<Set Sts Data>\nskill: 61,67,73\nskill 6: 95,96\n</Set Sts Data>\n\n<book:no>\n","params":[0,0,0,0,0,0,0,0],"price":0,"wtypeId":3},
{"id":17,"animationId":0,"description":"Powerful magic that may require materials.","etypeId":1,"traits":[{"code":31,"dataId":1,"value":0},{"code":22,"dataId":0,"value":0}],"iconIndex":79,"name":"High Magic","note":"<Set Sts Data>\nskill: 82,85,88\n</Set Sts Data>\n\n<book:no>\n","params":[0,0,0,0,0,0,0,0],"price":0,"wtypeId":3},
{"id":18,"animationId":0,"description":"","etypeId":1,"traits":[{"code":31,"dataId":1,"value":0},{"code":22,"dataId":0,"value":0}],"iconIndex":0,"name":"","note":"","params":[0,0,0,0,0,0,0,0],"price":0,"wtypeId":0},
{"id":19,"animationId":0,"description":"Enhance your basic stats.","etypeId":1,"traits":[{"code":31,"dataId":1,"value":0},{"code":22,"dataId":0,"value":0}],"iconIndex":97,"name":"Status","note":"<Set Sts Data>\nskill: 131,141,161,171,181\n</Set Sts Data>\n\n<book:no>\n","params":[0,0,0,0,0,0,0,0],"price":0,"wtypeId":3},
{"id":20,"animationId":0,"description":"","etypeId":1,"traits":[{"code":31,"dataId":1,"value":0},{"code":22,"dataId":0,"value":0}],"iconIndex":0,"name":"","note":"","params":[0,0,0,0,0,0,0,0],"price":0,"wtypeId":0},
{"id":21,"animationId":0,"description":"","etypeId":1,"traits":[],"iconIndex":0,"name":"Maximum HP + 10","note":"<book:no>\n","params":[10,0,0,0,0,0,0,0],"price":0,"wtypeId":4},
{"id":22,"animationId":0,"description":"","etypeId":1,"traits":[],"iconIndex":0,"name":"Maximum HP + 20","note":"<book:no>\n","params":[20,0,0,0,0,0,0,0],"price":0,"wtypeId":4},
{"id":23,"animationId":0,"description":"","etypeId":1,"traits":[],"iconIndex":0,"name":"Maximum HP + 30","note":"<book:no>\n","params":[30,0,0,0,0,0,0,0],"price":0,"wtypeId":4},
{"id":24,"animationId":0,"description":"","etypeId":1,"traits":[],"iconIndex":0,"name":"Maximum HP + 40","note":"<book:no>\n","params":[40,0,0,0,0,0,0,0],"price":0,"wtypeId":4},
{"id":25,"animationId":0,"description":"","etypeId":1,"traits":[],"iconIndex":0,"name":"Maximum HP + 50","note":"<book:no>\n","params":[50,0,0,0,0,0,0,0],"price":0,"wtypeId":4},
{"id":26,"animationId":0,"description":"","etypeId":1,"traits":[{"code":31,"dataId":1,"value":0},{"code":22,"dataId":0,"value":0}],"iconIndex":0,"name":"","note":"","params":[0,0,0,0,0,0,0,0],"price":0,"wtypeId":0},
{"id":27,"animationId":0,"description":"","etypeId":1,"traits":[{"code":31,"dataId":1,"value":0},{"code":22,"dataId":0,"value":0}],"iconIndex":0,"name":"","note":"","params":[0,0,0,0,0,0,0,0],"price":0,"wtypeId":0},
{"id":28,"animationId":0,"description":"","etypeId":1,"traits":[{"code":31,"dataId":1,"value":0},{"code":22,"dataId":0,"value":0}],"iconIndex":0,"name":"","note":"","params":[0,0,0,0,0,0,0,0],"price":0,"wtypeId":0},
{"id":29,"animationId":0,"description":"","etypeId":1,"traits":[{"code":31,"dataId":1,"value":0},{"code":22,"dataId":0,"value":0}],"iconIndex":0,"name":"","note":"","params":[0,0,0,0,0,0,0,0],"price":0,"wtypeId":0},
{"id":30,"animationId":0,"description":"","etypeId":1,"traits":[{"code":31,"dataId":1,"value":0},{"code":22,"dataId":0,"value":0}],"iconIndex":0,"name":"","note":"","params":[0,0,0,0,0,0,0,0],"price":0,"wtypeId":0},
{"id":31,"animationId":0,"description":"","etypeId":1,"traits":[],"iconIndex":0,"name":"Maximum MP + 10","note":"<book:no>\n","params":[0,10,0,0,0,0,0,0],"price":0,"wtypeId":4},
{"id":32,"animationId":0,"description":"","etypeId":1,"traits":[],"iconIndex":0,"name":"Maximum MP + 15","note":"<book:no>\n","params":[0,15,0,0,0,0,0,0],"price":0,"wtypeId":4},
{"id":33,"animationId":0,"description":"","etypeId":1,"traits":[],"iconIndex":0,"name":"Maximum MP + 20","note":"<book:no>\n","params":[0,20,0,0,0,0,0,0],"price":0,"wtypeId":4},
{"id":34,"animationId":0,"description":"","etypeId":1,"traits":[],"iconIndex":0,"name":"Maximum MP + 25","note":"<book:no>\n","params":[0,25,0,0,0,0,0,0],"price":0,"wtypeId":4},
{"id":35,"animationId":0,"description":"","etypeId":1,"traits":[],"iconIndex":0,"name":"Maximum MP + 30","note":"<book:no>\n","params":[0,30,0,0,0,0,0,0],"price":0,"wtypeId":4},
{"id":36,"animationId":0,"description":"","etypeId":1,"traits":[{"code":31,"dataId":1,"value":0},{"code":22,"dataId":0,"value":0}],"iconIndex":0,"name":"","note":"","params":[0,0,0,0,0,0,0,0],"price":0,"wtypeId":0},
{"id":37,"animationId":0,"description":"","etypeId":1,"traits":[{"code":31,"dataId":1,"value":0},{"code":22,"dataId":0,"value":0}],"iconIndex":0,"name":"","note":"","params":[0,0,0,0,0,0,0,0],"price":0,"wtypeId":0},
{"id":38,"animationId":0,"description":"","etypeId":1,"traits":[{"code":31,"dataId":1,"value":0},{"code":22,"dataId":0,"value":0}],"iconIndex":0,"name":"","note":"","params":[0,0,0,0,0,0,0,0],"price":0,"wtypeId":0},
{"id":39,"animationId":0,"description":"","etypeId":1,"traits":[{"code":31,"dataId":1,"value":0},{"code":22,"dataId":0,"value":0}],"iconIndex":0,"name":"","note":"","params":[0,0,0,0,0,0,0,0],"price":0,"wtypeId":0},
{"id":40,"animationId":0,"description":"","etypeId":1,"traits":[{"code":31,"dataId":1,"value":0},{"code":22,"dataId":0,"value":0}],"iconIndex":0,"name":"","note":"","params":[0,0,0,0,0,0,0,0],"price":0,"wtypeId":0},
{"id":41,"animationId":0,"description":"","etypeId":1,"traits":[],"iconIndex":0,"name":"Attack power + 5","note":"<book:no>\n","params":[0,0,5,0,0,0,0,0],"price":0,"wtypeId":4},
{"id":42,"animationId":0,"description":"","etypeId":1,"traits":[],"iconIndex":0,"name":"Attack power + 7","note":"<book:no>\n","params":[0,0,7,0,0,0,0,0],"price":0,"wtypeId":4},
{"id":43,"animationId":0,"description":"","etypeId":1,"traits":[],"iconIndex":0,"name":"Attack power + 10","note":"<book:no>\n","params":[0,0,10,0,0,0,0,0],"price":0,"wtypeId":4},
{"id":44,"animationId":0,"description":"","etypeId":1,"traits":[],"iconIndex":0,"name":"Attack power + 15","note":"<book:no>\n","params":[0,0,15,0,0,0,0,0],"price":0,"wtypeId":4},
{"id":45,"animationId":0,"description":"","etypeId":1,"traits":[],"iconIndex":0,"name":"Attack power + 20","note":"<book:no>\n","params":[0,0,20,0,0,0,0,0],"price":0,"wtypeId":4},
{"id":46,"animationId":0,"description":"","etypeId":1,"traits":[{"code":31,"dataId":1,"value":0},{"code":22,"dataId":0,"value":0}],"iconIndex":0,"name":"","note":"","params":[0,0,0,0,0,0,0,0],"price":0,"wtypeId":0},
{"id":47,"animationId":0,"description":"","etypeId":1,"traits":[{"code":31,"dataId":1,"value":0},{"code":22,"dataId":0,"value":0}],"iconIndex":0,"name":"","note":"","params":[0,0,0,0,0,0,0,0],"price":0,"wtypeId":0},
{"id":48,"animationId":0,"description":"","etypeId":1,"traits":[{"code":31,"dataId":1,"value":0},{"code":22,"dataId":0,"value":0}],"iconIndex":0,"name":"","note":"","params":[0,0,0,0,0,0,0,0],"price":0,"wtypeId":0},
{"id":49,"animationId":0,"description":"","etypeId":1,"traits":[{"code":31,"dataId":1,"value":0},{"code":22,"dataId":0,"value":0}],"iconIndex":0,"name":"","note":"","params":[0,0,0,0,0,0,0,0],"price":0,"wtypeId":0},
{"id":50,"animationId":0,"description":"","etypeId":1,"traits":[{"code":31,"dataId":1,"value":0},{"code":22,"dataId":0,"value":0}],"iconIndex":0,"name":"","note":"","params":[0,0,0,0,0,0,0,0],"price":0,"wtypeId":0},
{"id":51,"animationId":0,"description":"","etypeId":1,"traits":[],"iconIndex":0,"name":"Defense power + 5","note":"<book:no>\n","params":[0,0,0,5,0,0,0,0],"price":0,"wtypeId":4},
{"id":52,"animationId":0,"description":"","etypeId":1,"traits":[],"iconIndex":0,"name":"Defense power + 7","note":"<book:no>\n","params":[0,0,0,7,0,0,0,0],"price":0,"wtypeId":4},
{"id":53,"animationId":0,"description":"","etypeId":1,"traits":[],"iconIndex":0,"name":"Defense power + 10","note":"<book:no>\n","params":[0,0,0,10,0,0,0,0],"price":0,"wtypeId":4},
{"id":54,"animationId":0,"description":"","etypeId":1,"traits":[],"iconIndex":0,"name":"Defense power + 15","note":"<book:no>\n","params":[0,0,0,15,0,0,0,0],"price":0,"wtypeId":4},
{"id":55,"animationId":0,"description":"","etypeId":1,"traits":[],"iconIndex":0,"name":"Defense power + 20","note":"<book:no>\n","params":[0,0,0,20,0,0,0,0],"price":0,"wtypeId":4},
{"id":56,"animationId":0,"description":"","etypeId":1,"traits":[{"code":31,"dataId":1,"value":0},{"code":22,"dataId":0,"value":0}],"iconIndex":0,"name":"","note":"","params":[0,0,0,0,0,0,0,0],"price":0,"wtypeId":0},
{"id":57,"animationId":0,"description":"","etypeId":1,"traits":[{"code":31,"dataId":1,"value":0},{"code":22,"dataId":0,"value":0}],"iconIndex":0,"name":"","note":"","params":[0,0,0,0,0,0,0,0],"price":0,"wtypeId":0},
{"id":58,"animationId":0,"description":"","etypeId":1,"traits":[{"code":31,"dataId":1,"value":0},{"code":22,"dataId":0,"value":0}],"iconIndex":0,"name":"","note":"","params":[0,0,0,0,0,0,0,0],"price":0,"wtypeId":0},
{"id":59,"animationId":0,"description":"","etypeId":1,"traits":[{"code":31,"dataId":1,"value":0},{"code":22,"dataId":0,"value":0}],"iconIndex":0,"name":"","note":"","params":[0,0,0,0,0,0,0,0],"price":0,"wtypeId":0},
{"id":60,"animationId":0,"description":"","etypeId":1,"traits":[{"code":31,"dataId":1,"value":0},{"code":22,"dataId":0,"value":0}],"iconIndex":0,"name":"","note":"","params":[0,0,0,0,0,0,0,0],"price":0,"wtypeId":0},
{"id":61,"animationId":0,"description":"","etypeId":1,"traits":[],"iconIndex":0,"name":"Magical power + 5","note":"<book:no>\n","params":[0,0,0,0,5,0,0,0],"price":0,"wtypeId":4},
{"id":62,"animationId":0,"description":"","etypeId":1,"traits":[],"iconIndex":0,"name":"Magical power + 7","note":"<book:no>\n","params":[0,0,0,0,7,0,0,0],"price":0,"wtypeId":4},
{"id":63,"animationId":0,"description":"","etypeId":1,"traits":[],"iconIndex":0,"name":"Magical power + 10","note":"<book:no>\n","params":[0,0,0,0,10,0,0,0],"price":0,"wtypeId":4},
{"id":64,"animationId":0,"description":"","etypeId":1,"traits":[],"iconIndex":0,"name":"Magical power + 15","note":"<book:no>\n","params":[0,0,0,0,15,0,0,0],"price":0,"wtypeId":4},
{"id":65,"animationId":0,"description":"","etypeId":1,"traits":[],"iconIndex":0,"name":"Magical power + 20","note":"<book:no>\n","params":[0,0,0,0,20,0,0,0],"price":0,"wtypeId":4},
{"id":66,"animationId":0,"description":"","etypeId":1,"traits":[{"code":31,"dataId":1,"value":0},{"code":22,"dataId":0,"value":0}],"iconIndex":0,"name":"","note":"","params":[0,0,0,0,0,0,0,0],"price":0,"wtypeId":0},
{"id":67,"animationId":0,"description":"","etypeId":1,"traits":[{"code":31,"dataId":1,"value":0},{"code":22,"dataId":0,"value":0}],"iconIndex":0,"name":"","note":"","params":[0,0,0,0,0,0,0,0],"price":0,"wtypeId":0},
{"id":68,"animationId":0,"description":"","etypeId":1,"traits":[{"code":31,"dataId":1,"value":0},{"code":22,"dataId":0,"value":0}],"iconIndex":0,"name":"","note":"","params":[0,0,0,0,0,0,0,0],"price":0,"wtypeId":0},
{"id":69,"animationId":0,"description":"","etypeId":1,"traits":[{"code":31,"dataId":1,"value":0},{"code":22,"dataId":0,"value":0}],"iconIndex":0,"name":"","note":"","params":[0,0,0,0,0,0,0,0],"price":0,"wtypeId":0},
{"id":70,"animationId":0,"description":"","etypeId":1,"traits":[{"code":31,"dataId":1,"value":0},{"code":22,"dataId":0,"value":0}],"iconIndex":0,"name":"","note":"","params":[0,0,0,0,0,0,0,0],"price":0,"wtypeId":0},
{"id":71,"animationId":0,"description":"","etypeId":1,"traits":[],"iconIndex":0,"name":"Speed + 5","note":"<book:no>\n","params":[0,0,0,0,0,0,5,0],"price":0,"wtypeId":4},
{"id":72,"animationId":0,"description":"","etypeId":1,"traits":[],"iconIndex":0,"name":"Speed + 7","note":"<book:no>\n","params":[0,0,0,0,0,0,7,0],"price":0,"wtypeId":4},
{"id":73,"animationId":0,"description":"","etypeId":1,"traits":[],"iconIndex":0,"name":"Speed + 10","note":"<book:no>\n","params":[0,0,0,0,0,0,10,0],"price":0,"wtypeId":4},
{"id":74,"animationId":0,"description":"","etypeId":1,"traits":[],"iconIndex":0,"name":"Speed + 15","note":"<book:no>\n","params":[0,0,0,0,0,0,15,0],"price":0,"wtypeId":4},
{"id":75,"animationId":0,"description":"","etypeId":1,"traits":[],"iconIndex":0,"name":"Speed + 20","note":"<book:no>\n","params":[0,0,0,0,0,0,20,0],"price":0,"wtypeId":4},
{"id":76,"animationId":0,"description":"","etypeId":1,"traits":[{"code":31,"dataId":1,"value":0},{"code":22,"dataId":0,"value":0}],"iconIndex":0,"name":"","note":"","params":[0,0,0,0,0,0,0,0],"price":0,"wtypeId":0},
{"id":77,"animationId":0,"description":"","etypeId":1,"traits":[{"code":31,"dataId":1,"value":0},{"code":22,"dataId":0,"value":0}],"iconIndex":0,"name":"","note":"","params":[0,0,0,0,0,0,0,0],"price":0,"wtypeId":0},
{"id":78,"animationId":0,"description":"","etypeId":1,"traits":[{"code":31,"dataId":1,"value":0},{"code":22,"dataId":0,"value":0}],"iconIndex":0,"name":"","note":"","params":[0,0,0,0,0,0,0,0],"price":0,"wtypeId":0},
{"id":79,"animationId":0,"description":"","etypeId":1,"traits":[{"code":31,"dataId":1,"value":0},{"code":22,"dataId":0,"value":0}],"iconIndex":0,"name":"","note":"","params":[0,0,0,0,0,0,0,0],"price":0,"wtypeId":0},
{"id":80,"animationId":0,"description":"","etypeId":1,"traits":[{"code":31,"dataId":1,"value":0},{"code":22,"dataId":0,"value":0}],"iconIndex":0,"name":"","note":"","params":[0,0,0,0,0,0,0,0],"price":0,"wtypeId":0},
{"id":81,"animationId":0,"description":"","etypeId":1,"traits":[{"code":31,"dataId":1,"value":0},{"code":22,"dataId":0,"value":0}],"iconIndex":0,"name":"","note":"","params":[0,0,0,0,0,0,0,0],"price":0,"wtypeId":0},
{"id":82,"animationId":0,"description":"","etypeId":1,"traits":[{"code":31,"dataId":1,"value":0},{"code":22,"dataId":0,"value":0}],"iconIndex":0,"name":"","note":"","params":[0,0,0,0,0,0,0,0],"price":0,"wtypeId":0},
{"id":83,"animationId":0,"description":"","etypeId":1,"traits":[{"code":31,"dataId":1,"value":0},{"code":22,"dataId":0,"value":0}],"iconIndex":0,"name":"","note":"","params":[0,0,0,0,0,0,0,0],"price":0,"wtypeId":0},
{"id":84,"animationId":0,"description":"","etypeId":1,"traits":[{"code":31,"dataId":1,"value":0},{"code":22,"dataId":0,"value":0}],"iconIndex":0,"name":"","note":"","params":[0,0,0,0,0,0,0,0],"price":0,"wtypeId":0},
{"id":85,"animationId":0,"description":"","etypeId":1,"traits":[{"code":31,"dataId":1,"value":0},{"code":22,"dataId":0,"value":0}],"iconIndex":0,"name":"","note":"","params":[0,0,0,0,0,0,0,0],"price":0,"wtypeId":0},
{"id":86,"animationId":0,"description":"","etypeId":1,"traits":[{"code":31,"dataId":1,"value":0},{"code":22,"dataId":0,"value":0}],"iconIndex":0,"name":"","note":"","params":[0,0,0,0,0,0,0,0],"price":0,"wtypeId":0},
{"id":87,"animationId":0,"description":"","etypeId":1,"traits":[{"code":31,"dataId":1,"value":0},{"code":22,"dataId":0,"value":0}],"iconIndex":0,"name":"","note":"","params":[0,0,0,0,0,0,0,0],"price":0,"wtypeId":0},
{"id":88,"animationId":0,"description":"","etypeId":1,"traits":[{"code":31,"dataId":1,"value":0},{"code":22,"dataId":0,"value":0}],"iconIndex":0,"name":"","note":"","params":[0,0,0,0,0,0,0,0],"price":0,"wtypeId":0},
{"id":89,"animationId":0,"description":"","etypeId":1,"traits":[{"code":31,"dataId":1,"value":0},{"code":22,"dataId":0,"value":0}],"iconIndex":0,"name":"","note":"","params":[0,0,0,0,0,0,0,0],"price":0,"wtypeId":0},
{"id":90,"animationId":0,"description":"","etypeId":1,"traits":[{"code":31,"dataId":1,"value":0},{"code":22,"dataId":0,"value":0}],"iconIndex":0,"name":"","note":"","params":[0,0,0,0,0,0,0,0],"price":0,"wtypeId":0},
{"id":91,"animationId":0,"description":"","etypeId":1,"traits":[{"code":31,"dataId":1,"value":0},{"code":22,"dataId":0,"value":0}],"iconIndex":0,"name":"","note":"","params":[0,0,0,0,0,0,0,0],"price":0,"wtypeId":0},
{"id":92,"animationId":0,"description":"","etypeId":1,"traits":[{"code":31,"dataId":1,"value":0},{"code":22,"dataId":0,"value":0}],"iconIndex":0,"name":"","note":"","params":[0,0,0,0,0,0,0,0],"price":0,"wtypeId":0},
{"id":93,"animationId":0,"description":"","etypeId":1,"traits":[{"code":31,"dataId":1,"value":0},{"code":22,"dataId":0,"value":0}],"iconIndex":0,"name":"","note":"","params":[0,0,0,0,0,0,0,0],"price":0,"wtypeId":0},
{"id":94,"animationId":0,"description":"","etypeId":1,"traits":[{"code":31,"dataId":1,"value":0},{"code":22,"dataId":0,"value":0}],"iconIndex":0,"name":"","note":"","params":[0,0,0,0,0,0,0,0],"price":0,"wtypeId":0},
{"id":95,"animationId":0,"description":"","etypeId":1,"traits":[{"code":31,"dataId":1,"value":0},{"code":22,"dataId":0,"value":0}],"iconIndex":0,"name":"","note":"","params":[0,0,0,0,0,0,0,0],"price":0,"wtypeId":0},
{"id":96,"animationId":0,"description":"","etypeId":1,"traits":[{"code":31,"dataId":1,"value":0},{"code":22,"dataId":0,"value":0}],"iconIndex":0,"name":"","note":"","params":[0,0,0,0,0,0,0,0],"price":0,"wtypeId":0},
{"id":97,"animationId":0,"description":"","etypeId":1,"traits":[{"code":31,"dataId":1,"value":0},{"code":22,"dataId":0,"value":0}],"iconIndex":0,"name":"","note":"","params":[0,0,0,0,0,0,0,0],"price":0,"wtypeId":0},
{"id":98,"animationId":0,"description":"","etypeId":1,"traits":[{"code":31,"dataId":1,"value":0},{"code":22,"dataId":0,"value":0}],"iconIndex":0,"name":"","note":"","params":[0,0,0,0,0,0,0,0],"price":0,"wtypeId":0},
{"id":99,"animationId":0,"description":"","etypeId":1,"traits":[{"code":31,"dataId":1,"value":0},{"code":22,"dataId":0,"value":0}],"iconIndex":0,"name":"","note":"","params":[0,0,0,0,0,0,0,0],"price":0,"wtypeId":0},
{"id":100,"animationId":0,"description":"","etypeId":1,"traits":[{"code":31,"dataId":1,"value":0},{"code":22,"dataId":0,"value":0}],"iconIndex":0,"name":"","note":"","params":[0,0,0,0,0,0,0,0],"price":0,"wtypeId":0}
]